[
  {
    "id": 14,
    "name": "Breathe",
    "icon": "breathe"
  },
  {
    "id": 15,
    "name": "Hear",
    "icon": "hear"
  },
  {
    "id": 16,
    "name": "See",
    "icon": "see"
  },
  {
    "id": 17,
    "name": "Smell",
    "icon": "smell"
  },
  {
    "id": 18,
    "name": "Speak",
    "icon": "speak"
  },
  {
    "id": 19,
    "name": "Sleep",
    "icon": "sleep"
  },
  {
    "id": 20,
    "name": "Walk",
    "icon": "walk"
  },
  {
    "id": 21,
    "name": "Concentrate",
    "icon": "brain"
  },
  {
    "id": 22,
    "name": "Go to toilet properly",
    "icon": "toilet"
  },
  {
    "id": 23,
    "name": "Stop scratching",
    "icon": "itchy"
  },
  {
    "id": 24,
    "name": "Not on list",
    "icon": "more"
  }
]
